pagegen/Common.py
pagegen/Config.py
pagegen/DepGraph.py
pagegen/Page.py
pagegen/PgnHandler.py
pagegen/Plugins.py
pagegen/Site.py
pagegen/__init__.py
pagegen/constants.py
pagegen/logger_setup.py
pagegen/markdown_inline_convo.py
pagegen/markdown_inline_graphviz.py
pagegen/pagegen.py
pagegen/plugins/mako_templates/mako_templates.py
pagegen/plugins/minify/minify.py
pagegen/plugins/pgn_markdown/markdown_inline_convo.py
pagegen/plugins/pgn_markdown/markdown_inline_graphviz.py
pagegen/plugins/pgn_markdown/pgn_markdown.py
pagegen/plugins/rss/rss.py
pagegen/plugins/shortcodes/shortcodes.py
pagegen/plugins/shortcodes/shortcodes_built_in.py
pagegen/plugins/site_search/site_search.py
pagegen/plugins/sitemap/sitemap.py
pagegen/skel/site.conf
pagegen/skel/content/index.html
pagegen/skel/themes/kiss/assets/burger.svg
pagegen/skel/themes/kiss/assets/close.svg
pagegen/skel/themes/kiss/assets/favicon.ico
pagegen/skel/themes/kiss/assets/pgn-logo.svg
pagegen/skel/themes/kiss/assets/site.css
pagegen/skel/themes/kiss/assets/site.js
pagegen/skel/themes/kiss/templates/base.mako
pagegen/skel/themes/kiss/templates/pages.mako
pagegen-4.1.0.dist-info/METADATA
pagegen-4.1.0.dist-info/WHEEL
pagegen-4.1.0.dist-info/entry_points.txt
pagegen-4.1.0.dist-info/top_level.txt
pagegen-4.1.0.dist-info/RECORD
